nuaudit_python_autogen/__init__.py
nuaudit_python_autogen/api_client.py
nuaudit_python_autogen/configuration.py
nuaudit_python_autogen/exceptions.py
nuaudit_python_autogen/model_utils.py
nuaudit_python_autogen/rest.py
nuaudit_python_autogen/api/__init__.py
nuaudit_python_autogen/api/api_clients_api.py
nuaudit_python_autogen/api/api_keys_api.py
nuaudit_python_autogen/api/identities_api.py
nuaudit_python_autogen/api/invites_api.py
nuaudit_python_autogen/api/organizations_api.py
nuaudit_python_autogen/api/permissions_api.py
nuaudit_python_autogen/api/records_api.py
nuaudit_python_autogen/api/resources_api.py
nuaudit_python_autogen/api/roles_api.py
nuaudit_python_autogen/api/trails_api.py
nuaudit_python_autogen/api/users_api.py
nuaudit_python_autogen/apis/__init__.py
nuaudit_python_autogen/model/__init__.py
nuaudit_python_autogen/model/accept_invite_mutation.py
nuaudit_python_autogen/model/api_client.py
nuaudit_python_autogen/model/api_client_mutation.py
nuaudit_python_autogen/model/api_key.py
nuaudit_python_autogen/model/api_key_mutation.py
nuaudit_python_autogen/model/error_message.py
nuaudit_python_autogen/model/http_validation_error.py
nuaudit_python_autogen/model/identity.py
nuaudit_python_autogen/model/identity_record.py
nuaudit_python_autogen/model/identity_record_mutation.py
nuaudit_python_autogen/model/invite.py
nuaudit_python_autogen/model/invite_mutation.py
nuaudit_python_autogen/model/invite_status.py
nuaudit_python_autogen/model/metadata.py
nuaudit_python_autogen/model/organization.py
nuaudit_python_autogen/model/organization_mutation.py
nuaudit_python_autogen/model/permission.py
nuaudit_python_autogen/model/permission_deletion.py
nuaudit_python_autogen/model/permission_mutation.py
nuaudit_python_autogen/model/record.py
nuaudit_python_autogen/model/record_mutation.py
nuaudit_python_autogen/model/resource.py
nuaudit_python_autogen/model/resource_record.py
nuaudit_python_autogen/model/resource_record_mutation.py
nuaudit_python_autogen/model/role.py
nuaudit_python_autogen-1.0.0.dist-info/METADATA
nuaudit_python_autogen-1.0.0.dist-info/WHEEL
nuaudit_python_autogen-1.0.0.dist-info/top_level.txt
nuaudit_python_autogen-1.0.0.dist-info/RECORD
