Metadata-Version: 2.1
Name: nuaudit-python-autogen
Version: 1.0.0
Summary: Nuaudit
Home-page: UNKNOWN
Author: Nuaudit Support
Author-email: support@nuaudit.com
License: UNKNOWN
Keywords: OpenAPI,OpenAPI-Generator,Nuaudit
Platform: UNKNOWN
Requires-Python: >=3.6
Requires-Dist: urllib3 (>=1.25.3)
Requires-Dist: python-dateutil
